multireposearch
