Metadata-Version: 1.0
Name: trac-MultiRepoSearchPlugin
Version: 0.2.1
Summary: Search the text of source code in your Trac repositories (0.12 and up)
Home-page: http://trac-hacks.org/wiki/MultiRepoSearchPlugin
Author: Ethan Jucovy
Author-email: ejucovy@gmail.com
License: BSD
Platform: UNKNOWN
